README.md
setup.py
unitpay_python_sdk/__init__.py
unitpay_python_sdk/api.py
unitpay_python_sdk/exceptions.py
unitpay_python_sdk/utils.py
unitpay_python_sdk.egg-info/PKG-INFO
unitpay_python_sdk.egg-info/SOURCES.txt
unitpay_python_sdk.egg-info/dependency_links.txt
unitpay_python_sdk.egg-info/top_level.txt