Metadata-Version: 1.0
Name: unitpay-python-sdk
Version: 1.0.0
Summary: UnitPay Python SDK
Home-page: https://github.com/Underlor/unitpay_python_sdk
Author: Underlor
Author-email: cfyz_74@mail.ru
License: Creative Commons Attribution-Noncommercial-Share Alike license
Platform: UNKNOWN
